secure_string_cipher/__init__.py
secure_string_cipher/audit_log.py
secure_string_cipher/cli.py
secure_string_cipher/cli_args.py
secure_string_cipher/config.py
secure_string_cipher/core.py
secure_string_cipher/passphrase_generator.py
secure_string_cipher/passphrase_manager.py
secure_string_cipher/rate_limiter.py
secure_string_cipher/secure_memory.py
secure_string_cipher/security.py
secure_string_cipher/timing_safe.py
secure_string_cipher/utils.py
secure_string_cipher-1.0.32.dist-info/METADATA
secure_string_cipher-1.0.32.dist-info/WHEEL
secure_string_cipher-1.0.32.dist-info/entry_points.txt
secure_string_cipher-1.0.32.dist-info/licenses/LICENSE
secure_string_cipher-1.0.32.dist-info/RECORD
