Metadata-Version: 2.4
Name: secure-string-cipher
Version: 1.0.32
Summary: A secure AES-GCM encryption utility with user-friendly features
Project-URL: Homepage, https://github.com/TheRedTower/secure-string-cipher
Project-URL: Bug Tracker, https://github.com/TheRedTower/secure-string-cipher/issues
Project-URL: Documentation, https://github.com/TheRedTower/secure-string-cipher/wiki
Project-URL: Changelog, https://github.com/TheRedTower/secure-string-cipher/blob/main/CHANGELOG.md
Author-email: TheRedTower <security@avondenecloud.uk>
License: MIT License
License-File: LICENSE
Classifier: Development Status :: 4 - Beta
Classifier: Environment :: Console
Classifier: Intended Audience :: End Users/Desktop
Classifier: License :: OSI Approved :: MIT License
Classifier: Operating System :: OS Independent
Classifier: Programming Language :: Python :: 3
Classifier: Programming Language :: Python :: 3.12
Classifier: Programming Language :: Python :: 3.13
Classifier: Programming Language :: Python :: 3.14
Classifier: Topic :: Security :: Cryptography
Classifier: Topic :: Utilities
Requires-Python: >=3.12
Requires-Dist: argon2-cffi==25.1.0
Requires-Dist: cryptography==46.0.3
Requires-Dist: pynacl==1.6.1
Requires-Dist: pyperclip==1.11.0
Requires-Dist: urllib3==2.6.2
Requires-Dist: wcwidth==0.2.14
Provides-Extra: dev
Requires-Dist: detect-secrets==1.5.0; extra == 'dev'
Requires-Dist: hypothesis==6.146.0; extra == 'dev'
Requires-Dist: mypy==1.18.2; extra == 'dev'
Requires-Dist: pip-audit==2.9.0; extra == 'dev'
Requires-Dist: pre-commit>=4.5.0; extra == 'dev'
Requires-Dist: pytest-cov==7.0.0; extra == 'dev'
Requires-Dist: pytest-mock==3.15.1; extra == 'dev'
Requires-Dist: pytest-timeout==2.4.0; extra == 'dev'
Requires-Dist: pytest-xdist==3.8.0; extra == 'dev'
Requires-Dist: pytest==8.4.2; extra == 'dev'
Requires-Dist: ruff==0.14.3; extra == 'dev'
Provides-Extra: test
Requires-Dist: pytest-cov==7.0.0; extra == 'test'
Requires-Dist: pytest-timeout==2.4.0; extra == 'test'
Requires-Dist: pytest-xdist==3.8.0; extra == 'test'
Requires-Dist: pytest==8.4.2; extra == 'test'
